nvna/__init__.py
nvna/device.py
nvna/exceptions.py
nvna-1.1.2.dist-info/LICENSE
nvna-1.1.2.dist-info/METADATA
nvna-1.1.2.dist-info/WHEEL
nvna-1.1.2.dist-info/top_level.txt
nvna-1.1.2.dist-info/RECORD
